main.py
pdf_splitter_cli-0.1.3.dist-info/licenses/LICENSE
pdf_splitter_cli-0.1.3.dist-info/METADATA
pdf_splitter_cli-0.1.3.dist-info/WHEEL
pdf_splitter_cli-0.1.3.dist-info/entry_points.txt
pdf_splitter_cli-0.1.3.dist-info/top_level.txt
pdf_splitter_cli-0.1.3.dist-info/RECORD
