Metadata-Version: 2.4
Name: pdf-splitter-cli
Version: 0.1.3
Summary: A modern command-line tool to split PDF files into smaller chunks with progress bars and automatic filename generation
Author-email: Joao Machete <jmachete@gmail.com>
Maintainer-email: Joao Machete <jmachete@gmail.com>
License-Expression: MIT
Project-URL: Homepage, https://github.com/jmxt3/pdf-splitter
Project-URL: Repository, https://github.com/jmxt3/pdf-splitter.git
Project-URL: Issues, https://github.com/jmxt3/pdf-splitter/issues
Project-URL: Documentation, https://github.com/jmxt3/pdf-splitter#readme
Keywords: pdf,split,cli,command-line,pdf-tools,document-processing
Classifier: Development Status :: 4 - Beta
Classifier: Environment :: Console
Classifier: Intended Audience :: End Users/Desktop
Classifier: Intended Audience :: Developers
Classifier: Operating System :: OS Independent
Classifier: Programming Language :: Python :: 3
Classifier: Programming Language :: Python :: 3.8
Classifier: Programming Language :: Python :: 3.9
Classifier: Programming Language :: Python :: 3.10
Classifier: Programming Language :: Python :: 3.11
Classifier: Programming Language :: Python :: 3.12
Classifier: Programming Language :: Python :: 3.13
Classifier: Topic :: Multimedia :: Graphics
Classifier: Topic :: Office/Business
Classifier: Topic :: System :: Archiving
Classifier: Topic :: Utilities
Requires-Python: >=3.8
License-File: LICENSE
Requires-Dist: click>=8.0.0
Requires-Dist: pypdf>=3.0.0
Dynamic: license-file
